liuwangcs/__init__.py
liuwangcs/liuwangcs.py
liuwangcs-0.0.2.dist-info/METADATA
liuwangcs-0.0.2.dist-info/WHEEL
liuwangcs-0.0.2.dist-info/top_level.txt
liuwangcs-0.0.2.dist-info/RECORD
