Metadata-Version: 2.1
Name: liuwangcs
Version: 0.0.2
Summary: This is a project template.
Author: Gardenia
Author-email: 1198481467@qq.com
